alu.v
module alu (
  input [31:0] a, b,
  input [2:0] alu_ctrl,
  output reg [31:0] result
);
  always @(*) begin
    case (alu_ctrl)
      3'b000: result = a + b; // ADD
      3'b001: result = a - b; // SUB
      default: result = 0;
    endcase
  end
endmodule

ex_stage.v
module ex_stage (
  input [31:0] a, b,
  input [6:0] opcode,
  input [2:0] funct3,
  input [6:0] funct7,
  output [31:0] result,
  output reg [2:0] alu_ctrl
);

  alu alu_unit (
    .a(a),
    .b(b),
    .alu_ctrl(alu_ctrl),
    .result(result)
  );

  always @(*) begin
    alu_ctrl = 3'b000;
    if (opcode == 7'b0110011) begin // R-type
      if (funct3 == 3'b000 && funct7 == 7'b0000000)
        alu_ctrl = 3'b000; // ADD
      else if (funct3 == 3'b000 && funct7 == 7'b0100000)
        alu_ctrl = 3'b001; // SUB
    end
  end
endmodule

reg_file.v
module reg_file (
  input clk,
  input [4:0] rs1, rs2, rd,
  input [31:0] wd,
  input we,
  output [31:0] a, b
);
  reg [31:0] regs[0:31];

  assign a = regs[rs1];
  assign b = regs[rs2];

  initial begin
    regs[2] = 32'd10; // x2
    regs[3] = 32'd5;  // x3
    regs[5] = 32'd4;  // x5
    regs[7] = 32'd8;  // x7 (for lw base address)
  end

  always @(posedge clk) begin
    if (we)
      regs[rd] <= wd;
  end
endmodule

id_stage.v
module id_stage (
  input [31:0] instr,
  input [31:0] pc,
  output [4:0] rs1, rs2, rd,
  output [2:0] funct3,
  output [6:0] funct7,
  output [6:0] opcode
);
  assign opcode = instr[6:0];
  assign rd     = instr[11:7];
  assign funct3 = instr[14:12];
  assign rs1    = instr[19:15];
  assign rs2    = instr[24:20];
  assign funct7 = instr[31:25];
endmodule

if_stage.v
// R-type: add x1, x2, x3 | sub x4, x1, x5
// I-type: lw x6, 0(x7)

module if_stage (
  input clk,
  input reset,
  output reg [31:0] instr,
  output reg [31:0] pc_out
);

  reg [31:0] pc;
  reg [31:0] instr_mem[0:15];

  initial begin
    pc = 0;
    // Format: opcode + rs1 + rs2 + rd (simplified)
    instr_mem[0] = 32'b000000000011_00010_000_00001_0110011; // add x1, x2, x3
    instr_mem[1] = 32'b010000000101_00001_000_00100_0110011; // sub x4, x1, x5
    instr_mem[2] = 32'b000000000000_00111_010_00110_0000011; // lw x6, 0(x7)
  end

  always @(posedge clk or posedge reset) begin
    if (reset)
      pc <= 0;
    else
      pc <= pc + 4;
  end

  always @(*) begin
    instr = instr_mem[pc >> 2];
    pc_out = pc;
  end
endmodule

processor_top.v
module processor_top (
  input clk,
  input reset
);
  wire [31:0] instr, pc;
  wire [4:0] rs1, rs2, rd;
  wire [2:0] funct3, alu_ctrl;
  wire [6:0] funct7, opcode;
  wire [31:0] a, b, result;

  if_stage IF (.clk(clk), .reset(reset), .instr(instr), .pc_out(pc));
  id_stage ID (.instr(instr), .pc(pc), .rs1(rs1), .rs2(rs2), .rd(rd), .funct3(funct3), .funct7(funct7), .opcode(opcode));
  reg_file RF (.clk(clk), .rs1(rs1), .rs2(rs2), .rd(rd), .wd(result), .we(1'b1), .a(a), .b(b));
  ex_stage EX (.a(a), .b(b), .opcode(opcode), .funct3(funct3), .funct7(funct7), .result(result), .alu_ctrl(alu_ctrl));
endmodule

testbench.v
module testbench;
  reg clk, reset;

  processor_top dut (
    .clk(clk),
    .reset(reset)
  );

  initial begin
    $dumpfile("dump.vcd");
    $dumpvars(1, dut);
    $dumpvars(1, dut.IF);
    $dumpvars(1, dut.ID);
    $dumpvars(1, dut.EX);
    $dumpvars(1, dut.RF);
    $dumpvars(1, dut.pc);
    $dumpvars(1, dut.instr);
    $dumpvars(1, dut.result);
    $dumpvars(1, dut.rs1);
    $dumpvars(1, dut.rs2);
    $dumpvars(1, dut.rd);
    $dumpvars(1, dut.a);
    $dumpvars(1, dut.b);
    $dumpvars(1, dut.alu_ctrl);
    clk = 0;
    reset = 1;
    #5 reset = 0;
    #200 $finish;
  end

  always #5 clk = ~clk;
endmodule

dump.vcd
$date
	Tue Jul 15 15:26:01 2025
$end
$version
	Icarus Verilog
$end
$timescale
	1s
$end
$scope module testbench $end
$scope module dut $end
$var wire 1 ! clk $end
$var wire 1 " reset $end
$var wire 5 # rs2 [4:0] $end
$var wire 5 $ rs1 [4:0] $end
$var wire 32 % result [31:0] $end
$var wire 5 & rd [4:0] $end
$var wire 32 ' pc [31:0] $end
$var wire 7 ( opcode [6:0] $end
$var wire 32 ) instr [31:0] $end
$var wire 7 * funct7 [6:0] $end
$var wire 3 + funct3 [2:0] $end
$var wire 32 , b [31:0] $end
$var wire 3 - alu_ctrl [2:0] $end
$var wire 32 . a [31:0] $end
$upscope $end
$upscope $end
$scope module testbench $end
$scope module dut $end
$scope module IF $end
$var wire 1 ! clk $end
$var wire 1 " reset $end
$var reg 32 / instr [31:0] $end
$var reg 32 0 pc [31:0] $end
$var reg 32 1 pc_out [31:0] $end
$upscope $end
$upscope $end
$upscope $end
$scope module testbench $end
$scope module dut $end
$scope module ID $end
$var wire 5 2 rs2 [4:0] $end
$var wire 5 3 rs1 [4:0] $end
$var wire 5 4 rd [4:0] $end
$var wire 32 5 pc [31:0] $end
$var wire 7 6 opcode [6:0] $end
$var wire 32 7 instr [31:0] $end
$var wire 7 8 funct7 [6:0] $end
$var wire 3 9 funct3 [2:0] $end
$upscope $end
$upscope $end
$upscope $end
$scope module testbench $end
$scope module dut $end
$scope module EX $end
$var wire 32 : result [31:0] $end
$var wire 7 ; opcode [6:0] $end
$var wire 7 < funct7 [6:0] $end
$var wire 3 = funct3 [2:0] $end
$var wire 32 > b [31:0] $end
$var wire 32 ? a [31:0] $end
$var reg 3 @ alu_ctrl [2:0] $end
$upscope $end
$upscope $end
$upscope $end
$scope module testbench $end
$scope module dut $end
$scope module RF $end
$var wire 32 A a [31:0] $end
$var wire 32 B b [31:0] $end
$var wire 1 ! clk $end
$var wire 5 C rd [4:0] $end
$var wire 5 D rs1 [4:0] $end
$var wire 5 E rs2 [4:0] $end
$var wire 32 F wd [31:0] $end
$var wire 1 G we $end
$upscope $end
$upscope $end
$upscope $end
$enddefinitions $end
$comment Show the parameter values. $end
$dumpall
$end
#0
$dumpvars
1G
b1111 F
b11 E
b10 D
b1 C
b101 B
b1010 A
b0 @
b1010 ?
b101 >
b0 =
b0 <
b110011 ;
b1111 :
b0 9
b0 8
b1100010000000010110011 7
b110011 6
b0 5
b1 4
b10 3
b11 2
b0 1
b0 0
b1100010000000010110011 /
b1010 .
b0 -
b101 ,
b0 +
b0 *
b1100010000000010110011 )
b110011 (
b0 '
b1 &
b1111 %
b10 $
b11 #
1"
0!
$end
#5
b1 -
b1 @
b1011 %
b1011 :
b1011 F
b100000 *
b100000 8
b100000 <
b100 ,
b100 >
b100 B
b101 #
b101 2
b101 E
b1111 .
b1111 ?
b1111 A
b1 $
b1 3
b1 D
b100 &
b100 4
b100 C
b100 '
b100 1
b100 5
b1000000010100001000001000110011 )
b1000000010100001000001000110011 /
b1000000010100001000001000110011 7
b100 0
1!
0"
#10
0!
#15
bx %
bx :
bx F
b0 -
b0 @
b0 *
b0 8
b0 <
bx ,
bx >
bx B
b0 #
b0 2
b0 E
b1000 .
b1000 ?
b1000 A
b111 $
b111 3
b111 D
b10 +
b10 9
b10 =
b110 &
b110 4
b110 C
b11 (
b11 6
b11 ;
b1000 '
b1000 1
b1000 5
b111010001100000011 )
b111010001100000011 /
b111010001100000011 7
b1000 0
1!
#20
0!
#25
bx *
bx 8
bx <
bx #
bx 2
bx E
bx .
bx ?
bx A
bx $
bx 3
bx D
bx +
bx 9
bx =
bx &
bx 4
bx C
bx (
bx 6
bx ;
b1100 '
b1100 1
b1100 5
bx )
bx /
bx 7
b1100 0
1!
#30
0!
#35
b10000 '
b10000 1
b10000 5
b10000 0
1!
#40
0!
#45
b10100 '
b10100 1
b10100 5
b10100 0
1!
#50
0!
#55
b11000 '
b11000 1
b11000 5
b11000 0
1!
#60
0!
#65
b11100 '
b11100 1
b11100 5
b11100 0
1!
#70
0!
#75
b100000 '
b100000 1
b100000 5
b100000 0
1!
#80
0!
#85
b100100 '
b100100 1
b100100 5
b100100 0
1!
#90
0!
#95
b101000 '
b101000 1
b101000 5
b101000 0
1!
#100
0!
#105
b101100 '
b101100 1
b101100 5
b101100 0
1!
#110
0!
#115
b110000 '
b110000 1
b110000 5
b110000 0
1!
#120
0!
#125
b110100 '
b110100 1
b110100 5
b110100 0
1!
#130
0!
#135
b111000 '
b111000 1
b111000 5
b111000 0
1!
#140
0!
#145
b111100 '
b111100 1
b111100 5
b111100 0
1!
#150
0!
#155
b1000000 '
b1000000 1
b1000000 5
b1000000 0
1!
#160
0!
#165
b1000100 '
b1000100 1
b1000100 5
b1000100 0
1!
#170
0!
#175
b1001000 '
b1001000 1
b1001000 5
b1001000 0
1!
#180
0!
#185
b1001100 '
b1001100 1
b1001100 5
b1001100 0
1!
#190
0!
#195
b1010000 '
b1010000 1
b1010000 5
b1010000 0
1!
#200
0!
#205
b1010100 '
b1010100 1
b1010100 5
b1010100 0
1!
